odoo/addons/mgmtsystem_info_security_manual/README.rst
odoo/addons/mgmtsystem_info_security_manual/__init__.py
odoo/addons/mgmtsystem_info_security_manual/__manifest__.py
odoo/addons/mgmtsystem_info_security_manual/data/information_security_manual.xml
odoo/addons/mgmtsystem_info_security_manual/i18n/it.po
odoo/addons/mgmtsystem_info_security_manual/i18n/mgmtsystem_info_security_manual.pot
odoo/addons/mgmtsystem_info_security_manual/i18n/sv.po
odoo/addons/mgmtsystem_info_security_manual/readme/CONTRIBUTORS.md
odoo/addons/mgmtsystem_info_security_manual/readme/DESCRIPTION.md
odoo/addons/mgmtsystem_info_security_manual/readme/USAGE.md
odoo/addons/mgmtsystem_info_security_manual/static/description/icon.png
odoo/addons/mgmtsystem_info_security_manual/static/description/index.html
odoo_addon_mgmtsystem_info_security_manual-18.0.1.0.0.3.dist-info/METADATA
odoo_addon_mgmtsystem_info_security_manual-18.0.1.0.0.3.dist-info/WHEEL
odoo_addon_mgmtsystem_info_security_manual-18.0.1.0.0.3.dist-info/top_level.txt
odoo_addon_mgmtsystem_info_security_manual-18.0.1.0.0.3.dist-info/RECORD
